collab_learning_extension/__init__.py
collab_learning_extension/_version.py
collab_learning_extension/document.py
collab_learning_extension-0.2.7.data/data/share/jupyter/labextensions/collab_learning_extension/package.json
collab_learning_extension-0.2.7.data/data/share/jupyter/labextensions/collab_learning_extension/static/100.1238dc8150c6ee05f2f3.js
collab_learning_extension-0.2.7.data/data/share/jupyter/labextensions/collab_learning_extension/static/100.1238dc8150c6ee05f2f3.js.LICENSE.txt
collab_learning_extension-0.2.7.data/data/share/jupyter/labextensions/collab_learning_extension/static/135.0c1b37f6d6a76f12a3c5.js
collab_learning_extension-0.2.7.data/data/share/jupyter/labextensions/collab_learning_extension/static/135.0c1b37f6d6a76f12a3c5.js.LICENSE.txt
collab_learning_extension-0.2.7.data/data/share/jupyter/labextensions/collab_learning_extension/static/19.71ad51869806f64c2d2d.js
collab_learning_extension-0.2.7.data/data/share/jupyter/labextensions/collab_learning_extension/static/25.ec288a5496bcc8207525.js
collab_learning_extension-0.2.7.data/data/share/jupyter/labextensions/collab_learning_extension/static/400.88a065a037cc5a23c20c.js
collab_learning_extension-0.2.7.data/data/share/jupyter/labextensions/collab_learning_extension/static/433.f337c3aef4af7770213f.js
collab_learning_extension-0.2.7.data/data/share/jupyter/labextensions/collab_learning_extension/static/828.f33bf0ec3f9872ce9ef6.js
collab_learning_extension-0.2.7.data/data/share/jupyter/labextensions/collab_learning_extension/static/838.9297eb66e0f1910e5833.js
collab_learning_extension-0.2.7.data/data/share/jupyter/labextensions/collab_learning_extension/static/838.9297eb66e0f1910e5833.js.LICENSE.txt
collab_learning_extension-0.2.7.data/data/share/jupyter/labextensions/collab_learning_extension/static/873.ee8df56c63b89d937542.js
collab_learning_extension-0.2.7.data/data/share/jupyter/labextensions/collab_learning_extension/static/873.ee8df56c63b89d937542.js.LICENSE.txt
collab_learning_extension-0.2.7.dist-info/METADATA
collab_learning_extension-0.2.7.dist-info/WHEEL
collab_learning_extension-0.2.7.dist-info/entry_points.txt
collab_learning_extension-0.2.7.dist-info/licenses/LICENSE
collab_learning_extension-0.2.7.dist-info/RECORD
