Metadata-Version: 2.3
Name: collab_learning_extension
Version: 0.2.7
Dynamic: Keywords
Summary: A Collaborative Learning Extension for Jupyter Notebook
Project-URL: Homepage, https://github.com/ETH-PEACH-Lab/collaborative-learning-extension-jupyter
Project-URL: Bug Tracker, https://github.com/ETH-PEACH-Lab/collaborative-learning-extension-jupyter/issues
Project-URL: Repository, https://github.com/ETH-PEACH-Lab/collaborative-learning-extension-jupyter.git
Author-email: Pascal Linder <linderp@student.ethz.ch>
License: BSD 3-Clause License
License-File: LICENSE
Classifier: Framework :: Jupyter
Classifier: Framework :: Jupyter :: JupyterLab
Classifier: Framework :: Jupyter :: JupyterLab :: 4
Classifier: Framework :: Jupyter :: JupyterLab :: Extensions
Classifier: Framework :: Jupyter :: JupyterLab :: Extensions :: Prebuilt
Classifier: License :: OSI Approved :: BSD License
Classifier: Programming Language :: Python
Classifier: Programming Language :: Python :: 3
Classifier: Programming Language :: Python :: 3.8
Classifier: Programming Language :: Python :: 3.9
Classifier: Programming Language :: Python :: 3.10
Classifier: Programming Language :: Python :: 3.11
Classifier: Programming Language :: Python :: 3.12
Requires-Python: >=3.8
Requires-Dist: jupyter-collaboration<3,>=2.0.0
Requires-Dist: jupyter-ydoc<3,>=2
Requires-Dist: y-py
